fastapi_sse.py
fastapi_sse-1.1.1.dist-info/METADATA
fastapi_sse-1.1.1.dist-info/WHEEL
fastapi_sse-1.1.1.dist-info/licenses/LICENSE
fastapi_sse-1.1.1.dist-info/RECORD
