Metadata-Version: 2.3
Name: fastapi-sse
Version: 1.1.1
Summary: A tiny library for sending Server-Sent Events (SSE) in FastAPI
Project-URL: Homepage, https://github.com/MatthewScholefield/fastapi-sse
Author-email: "Matthew D. Scholefield" <matthew331199@gmail.com>
License: MIT
License-File: LICENSE
Classifier: Development Status :: 3 - Alpha
Classifier: Intended Audience :: Developers
Classifier: Programming Language :: Python :: 3
Classifier: Programming Language :: Python :: 3.10
Classifier: Programming Language :: Python :: 3.11
Classifier: Programming Language :: Python :: 3.12
Requires-Python: >=3.10
Requires-Dist: fastapi>=0.51.0
